charming_traceback/__init__.py
charming_traceback/installation.py
charming_traceback/styles.py
charming_traceback/traceback.py
charming_traceback-0.1.8.dist-info/WHEEL
charming_traceback-0.1.8.dist-info/METADATA
charming_traceback-0.1.8.dist-info/RECORD
