Metadata-Version: 2.3
Name: charming-traceback
Version: 0.1.8
Summary: Rich traceback adapted for PyCharm IDE by JetBrains
Author: Yevhen Bondarenko
Author-email: Yevhen Bondarenko <zekbond@gmail.com>
Requires-Dist: rich>=14.2.0
Requires-Python: >=3.11
